Matematica/__init__.py
Matematica-0.9.3.dist-info/LICENSE
Matematica-0.9.3.dist-info/METADATA
Matematica-0.9.3.dist-info/WHEEL
Matematica-0.9.3.dist-info/top_level.txt
Matematica-0.9.3.dist-info/RECORD
