Metadata-Version: 2.1
Name: Matematica
Version: 0.9.3
Summary: A simple, and powerful, math library
Home-page: https://github.com/CaioVieiraF/MathLib
Author: Caio Vieira
Author-email: caiovieiraproficional@protonmail.com
License: UNKNOWN
Platform: UNKNOWN
Classifier: Programming Language :: Python :: 3
Classifier: License :: OSI Approved :: MIT License
Classifier: Operating System :: OS Independent
Requires-Python: >=3.6
